nclib/__init__.py
nclib/errors.py
nclib/logger.py
nclib/netcat.py
nclib/process.py
nclib/py.typed
nclib/select.py
nclib/server.py
nclib/simplesock.py
nclib-1.0.8.data/scripts/serve-stdio
nclib-1.0.8.dist-info/licenses/LICENSE
nclib-1.0.8.dist-info/METADATA
nclib-1.0.8.dist-info/WHEEL
nclib-1.0.8.dist-info/top_level.txt
nclib-1.0.8.dist-info/RECORD
