Metadata-Version: 2.4
Name: nclib
Version: 1.0.8
Summary: Netcat as a library: convienent socket interfaces
Home-page: https://github.com/rhelmot/nclib
Author: rhelmot
Author-email: audrey@rhelmot.io
License: MIT
Keywords: netcat nc socket sock file pipe tcp udp recv until logging interact handle listen connect server serve stdio process gdb
Requires-Python: >=3.5
License-File: LICENSE
Dynamic: author
Dynamic: author-email
Dynamic: description
Dynamic: home-page
Dynamic: keywords
Dynamic: license
Dynamic: license-file
Dynamic: requires-python
Dynamic: summary
